ociedoo/__init__.py
ociedoo/__main__.py
ociedoo/check.py
ociedoo/cli.py
ociedoo/complete.py
ociedoo/defaults/config
ociedoo/lib.py
ociedoo-0.7.0.dist-info/entry_points.txt
ociedoo-0.7.0.dist-info/LICENSE
ociedoo-0.7.0.dist-info/WHEEL
ociedoo-0.7.0.dist-info/METADATA
ociedoo-0.7.0.dist-info/RECORD
