Metadata-Version: 2.1
Name: ociedoo
Version: 0.7.0
Summary: CLI tool to simplify the management of Odoo
Home-page: https://gitlab.com/coopiteasy/ociedoo
License: GPL-3.0-or-later
Keywords: cli,odoo,coopiteasy
Author: Coop IT Easy SCRLfs
Author-email: remy@coopiteasy.be
Maintainer: Rémy Taymans
Maintainer-email: remy@coopiteasy.be
Requires-Python: >=3.5,<4.0
Classifier: Development Status :: 5 - Production/Stable
Classifier: Intended Audience :: End Users/Desktop
Classifier: License :: OSI Approved :: GNU General Public License v3 or later (GPLv3+)
Classifier: Operating System :: POSIX
Classifier: Operating System :: Unix
Classifier: Programming Language :: Python :: 3
Classifier: Programming Language :: Python :: 3.5
Classifier: Programming Language :: Python :: 3.6
Classifier: Programming Language :: Python :: 3.7
Classifier: Programming Language :: Python :: 3.8
Classifier: Programming Language :: Python :: 3.9
Classifier: Programming Language :: Python :: Implementation :: CPython
Requires-Dist: click (>=7.0,<8.0)
Requires-Dist: passlib (>=1.7.4,<2.0.0)
Requires-Dist: prgconfig (>=1.0.0-beta.2,<2.0.0)
Requires-Dist: sh (>=1.12,<2.0)
Project-URL: Repository, https://gitlab.com/coopiteasy/ociedoo
